bomba-1.1.112.data/scripts/bomba
bombilla/__init__.py
bombilla/bombilla.py
bombilla/node.py
bombilla/parser.py
bombilla/__pycache__/__init__.cpython-310.pyc
bombilla/__pycache__/bombilla.cpython-310.pyc
bombilla/__pycache__/node.cpython-310.pyc
bombilla/utils/__init__.py
bombilla/utils/bunch.py
bombilla/utils/utils.py
bombilla/utils/__pycache__/__init__.cpython-310.pyc
bombilla/utils/__pycache__/utils.cpython-310.pyc
bomba-1.1.112.dist-info/METADATA
bomba-1.1.112.dist-info/WHEEL
bomba-1.1.112.dist-info/top_level.txt
bomba-1.1.112.dist-info/RECORD
